<markers><marker id="1" name="amiens - polyclinique picardie" address= "" lat="49.871264" lng="2.297086"  activity="rispacs"  version="v7"  /><marker id="13" name="beaune - cim pays beaunois" address= "" lat="47.032913" lng="4.832907"  activity="rispacs"  version="v7"  /><marker id="26" name="charenton - imagerie charenton" address= "" lat="48.823067" lng="2.417961"  activity="rispacs"  version="v7"  /><marker id="39" name="guadeloupe - cabinet natali" address= "" lat="16.237232" lng="-61.531561"  activity="rispacs"  version="v7"  /><marker id="41" name="guadeloupe - clinique acacias" address= "" lat="16.256647" lng="-61.588838"  activity="rispacs"  version="v7"  /><marker id="44" name="guadeloupe - scanner pointe-a-pitre" address= "" lat="16.243552" lng="-61.532687"  activity="rispacs"  version="v7"  /><marker id="49" name="levallois - imagerie ipade" address= "Levallois" lat="48.899190" lng="2.282061"  activity="rispacs"  version="v7"  /><marker id="65" name="montauban - clinique dr cave" address= "" lat="44.011858" lng="1.362979"  activity="rispacs"  version="v7"  /><marker id="66" name="mt de marsan - imagerie du marsan" address= "Hiroire" lat="43.891094" lng="-0.479452"  activity="rispacs"  version="v7"  /><marker id="67" name="mt de marsan - imagerie du marsan" address= "Clinique des Landes" lat="43.871629" lng="-0.484938"  activity="rispacs"  version="v7"  /><marker id="68" name="mt de marsan - imagerie du marsan" address= "IRM / Scanner du Marsan" lat="43.871428" lng="-0.484581"  activity="rispacs"  version="v7"  /><marker id="69" name="mt de marsan - imagerie du marsan" address= "St Sever" lat="43.757118" lng="-0.571398"  activity="rispacs"  version="v7"  /><marker id="75" name="paris - cim vouillé" address= "" lat="48.834152" lng="2.307499"  activity="rispacs"  version="v7"  /><marker id="79" name="paris - clinique alma" address= "" lat="48.861217" lng="2.305625"  activity="rispacs"  version="v7"  /><marker id="81" name="paris - clinique lilas" address= "" lat="48.878898" lng="2.422594"  activity="rispacs"  version="v7"  /><marker id="83" name="paris - scanner convention" address= "" lat="48.844034" lng="2.282202"  activity="rispacs"  version="v7"  /><marker id="89" name="perigueux - cim perigueux" address= "Cabinet Pompidou" lat="45.190054" lng="0.724915"  activity="rispacs"  version="v7"  /><marker id="90" name="perigueux - cim perigueux" address= "CH Perigueux" lat="45.193182" lng="0.730709"  activity="rispacs"  version="v7"  /><marker id="91" name="perigueux - cim perigueux" address= "Clinique du Parc" lat="45.188952" lng="0.728091"  activity="rispacs"  version="v7"  /><marker id="102" name="pessac - cim pessac/bdx" address= "Pessac" lat="44.802693" lng="-0.648745"  activity="rispacs"  version="v7"  /><marker id="103" name="pessac - cim pessac/bdx" address= "Caudéran" lat="44.858380" lng="-0.625337"  activity="rispacs"  version="v7"  /><marker id="106" name="réunion - imagerie savannah" address= "" lat="-20.986574" lng="55.296354"  activity="rispacs"  version="v7"  /><marker id="116" name="st martin - centre cimin" address= "St martin" lat="18.067390" lng="-63.082635"  activity="rispacs"  version="v7"  /><marker id="120" name="thiais - sotoval hop.privé" address= "Scanner / IRM" lat="48.768695" lng="2.370735"  activity="rispacs"  version="v7"  /><marker id="129" name="paris - institut arthur vernes" address= "" lat="48.847603" lng="2.329571"  activity="rispacs"  version="v7"  /><marker id="131" name="epinay - cim devexin" address= "Epinay" lat="48.956078" lng="2.296895"  activity="rispacs"  version="v7"  /><marker id="132" name="epinay - cim devexin" address= "Gargenville" lat="48.988750" lng="1.812809"  activity="rispacs"  version="v7"  /><marker id="133" name="côte d'ivoire - abidjan hmeb" address= "" lat="5.361856" lng="-3.883261"  activity="rispacs"  version="v7"  /><marker id="138" name="bastia - radiologie corse" address= "IRM Maymard CIPHC" lat="42.700381" lng="9.446945"  activity="rispacs"  version="v7"  /><marker id="139" name="bastia - radiologie corse" address= "Scanner Maymard" lat="42.700381" lng="9.446945"  activity="rispacs"  version="v7"  /><marker id="140" name="bastia - radiologie corse" address= "Radiologie Maymard" lat="42.700381" lng="9.446945"  activity="rispacs"  version="v7"  /><marker id="141" name="bastia - radiologie corse" address= "CIM Borgo" lat="42.550775" lng="9.441449"  activity="rispacs"  version="v7"  /><marker id="142" name="bastia - radiologie corse" address= "Cabinet du Centre" lat="42.705998" lng="9.452488"  activity="rispacs"  version="v7"  /><marker id="143" name="bastia - radiologie corse" address= "CH de Corte" lat="42.301758" lng="9.154275"  activity="rispacs"  version="v7"  /><marker id="144" name="bastia - radiologie corse" address= "Polyclinique de Furiani" lat="42.660168" lng="9.443046"  activity="rispacs"  version="v7"  /><marker id="145" name="bastia - radiologie corse" address= "Ile Rousse Balagne" lat="42.628896" lng="8.930461"  activity="rispacs"  version="v7"  /><marker id="146" name="annecy - radiologie74 seynod" address= "Annecy-Le-Vieux" lat="45.912521" lng="6.142083"  activity="rispacs"  version="v7"  /><marker id="147" name="annecy - radiologie74 seynod" address= "Seynod" lat="45.887952" lng=" 6.100480"  activity="rispacs"  version="v7"  /><marker id="148" name="annecy - radiologie74 seynod" address= "Rumilly" lat="45.864620" lng="5.936719"  activity="rispacs"  version="v7"  /><marker id="151" name="st martin - centre cimin" address= "St barth" lat="17.895963" lng="-62.852133"  activity="rispacs"  version="v7"  /><marker id="155" name="tarascon - cim tarascon" address= "" lat="43.803018" lng="4.656799"  activity="rispacs"  version="v7"  /><marker id="157" name="levallois - imagerie ipade" address= "La defense" lat="48.891379" lng="2.241917"  activity="rispacs"  version="v7"  /><marker id="166" name="guadeloupe - irm basse terre" address= "" lat="16.003597" lng="-61.728538"  activity="rispacs"  version="v7"  /><marker id="167" name="thiais - sotoval hop.privé" address= "Radiologie BSMS" lat="48.768797" lng="2.370035"  activity="rispacs"  version="v7"  /></markers>